fabricatio_rule/__init__.py
fabricatio_rule/config.py
fabricatio_rule/py.typed
fabricatio_rule/actions/__init__.py
fabricatio_rule/actions/rules.py
fabricatio_rule/capabilities/__init__.py
fabricatio_rule/capabilities/censor.py
fabricatio_rule/capabilities/check.py
fabricatio_rule/models/__init__.py
fabricatio_rule/models/kwargs_types.py
fabricatio_rule/models/patch.py
fabricatio_rule/models/rule.py
tests/test_check.py
tests/test_ruleset.py
fabricatio_rule-0.1.12.dist-info/METADATA
fabricatio_rule-0.1.12.dist-info/WHEEL
fabricatio_rule-0.1.12.dist-info/licenses/LICENSE
fabricatio_rule-0.1.12.dist-info/RECORD
