Metadata-Version: 2.4
Name: fabricatio-rule
Version: 0.1.12
Summary: A Python module for rule-based content validation, correction, and enforcement in LLM applications.
Project-URL: Homepage, https://github.com/Whth/fabricatio
Project-URL: Repository, https://github.com/Whth/fabricatio
Project-URL: Issues, https://github.com/Whth/fabricatio/issues
Author-email: Whth <zettainspector@foxmail.com>
License: MIT License
License-File: LICENSE
Requires-Python: <3.15,>=3.12
Requires-Dist: fabricatio-capabilities
Requires-Dist: fabricatio-core
Requires-Dist: fabricatio-improve
Requires-Dist: fabricatio-judge
